discord_db.py
discord_db-0.1.0.dist-info/WHEEL
discord_db-0.1.0.dist-info/METADATA
discord_db-0.1.0.dist-info/RECORD
