Metadata-Version: 2.1
Name: discord-db
Version: 0.1.0
Summary: Helpfull db writen on sqlite3, already has channel vars, global user vars, server user vars and server vars
Author: EditedCocktail
Requires-Python: >=3.8,<4.0
Classifier: Programming Language :: Python :: 3
Classifier: Programming Language :: Python :: 3.8
Classifier: Programming Language :: Python :: 3.9
